observe_traces/__init__.py
observe_traces/base/__init__.py
observe_traces/base/provider.py
observe_traces/base/tracer.py
observe_traces/config/__init__.py
observe_traces/config/context_util.py
observe_traces/config/langfuse_init.py
observe_traces/config/langfuse_service.py
observe_traces/config/utils.py
observe_traces/constants/__init__.py
observe_traces/langfuse/__init__.py
observe_traces/langfuse/logApiCall.py
observe_traces/middleware/__init__.py
observe_traces/middleware/middleware.py
observe_traces/providers/__init__.py
observe_traces/providers/embedding_providers.py
observe_traces/providers/llm_providers.py
observe_traces/providers/reranking_providers.py
observe_traces/providers/vectordb_providers.py
observe_traces/service/__init__.py
observe_traces/service/service_manager.py
observe_traces/tracers/__init__.py
observe_traces/tracers/embedding_tracer.py
observe_traces/tracers/general_tracer.py
observe_traces/tracers/llm_tracer.py
observe_traces/tracers/reranking_tracer.py
observe_traces/tracers/vectordb_tracer.py
observe_traces/utils/__init__.py
observe_traces/utils/token_costs.py
observe_traces/utils/tool_call_parser.py
observe_traces/utils/tracer_utils.py
observellm-1.2.8.dist-info/licenses/LICENSE
observellm-1.2.8.dist-info/METADATA
observellm-1.2.8.dist-info/WHEEL
observellm-1.2.8.dist-info/top_level.txt
observellm-1.2.8.dist-info/RECORD
